curt/__init__.py
curt/dictionary_creator.py
curt/graphs_generator.py
curt/html_creator.py
curt/repeated_timer.py
curt/reports.py
curt/simple_rest.py
curt/stats_generator.py
curt/thread_safe_data.py
curt/threads_manager.py
curt-0.0.5.dist-info/licenses/LICENSE
curt-0.0.5.dist-info/METADATA
curt-0.0.5.dist-info/WHEEL
curt-0.0.5.dist-info/top_level.txt
curt-0.0.5.dist-info/RECORD
