Metadata-Version: 2.4
Name: curt
Version: 0.0.5
Summary: CuRT allows to generate a specific number of RPS to a webservice. Permite generar un número específico de peticiones por segundo a un servicio web.
Author-email: Jahaziel Alvarez <jahaziel.alvarez@proton.me>
Project-URL: Homepage, https://gitlab.com/jahaziel-alvarez/curt
Project-URL: Bug Tracker, https://gitlab.com/jahaziel-alvarez/curt/issues
Classifier: Programming Language :: Python :: 3
Classifier: License :: OSI Approved :: MIT License
Classifier: Operating System :: OS Independent
Requires-Python: >=3.13
License-File: LICENSE
Requires-Dist: pandas>=2.3.1
Requires-Dist: plotly>=6.2.0
Requires-Dist: requests>=2.32.4
Dynamic: license-file
